aiopyami/__init__.py
aiopyami/ami.py
aiopyami/client.py
aiopyami/events.py
aiopyami/exceptions.py
aiopyami/formats.py
aiopyami/internal.py
aiopyami/utils.py
aiopyami-0.1.4.dist-info/LICENSE
aiopyami-0.1.4.dist-info/METADATA
aiopyami-0.1.4.dist-info/WHEEL
aiopyami-0.1.4.dist-info/top_level.txt
aiopyami-0.1.4.dist-info/RECORD
